Metadata-Version: 1.0
Name: evt73-distributions
Version: 1.1
Summary: Gaussian and Binomial distributions
Home-page: UNKNOWN
Author: Everton Mendes
Author-email: evertonmendes73@usp.br
License: UNKNOWN
Platform: UNKNOWN
